eldom/__init__.py
eldom/client.py
tests/__init__.py
tests/test_client.py
python_eldom-0.0.4.dist-info/LICENSE
python_eldom-0.0.4.dist-info/METADATA
python_eldom-0.0.4.dist-info/WHEEL
python_eldom-0.0.4.dist-info/top_level.txt
python_eldom-0.0.4.dist-info/RECORD
