Metadata-Version: 2.1
Name: python-eldom
Version: 0.0.4
Summary: A Python client for the Eldom API
Home-page: https://github.com/qbaware/pyeldom
Author: Daniel Gospodinow
Author-email: danielgospodinow@gmail.com
License: UNKNOWN
Platform: UNKNOWN
Classifier: Programming Language :: Python :: 3
Classifier: License :: OSI Approved :: MIT License
Classifier: Operating System :: OS Independent
Requires-Python: >=3.6
Requires-Dist: requests
